knn/__init__.py
knn/a.txt
knn/distances.py
knn/index.bl
knn_rk47-11.dist-info/METADATA
knn_rk47-11.dist-info/WHEEL
knn_rk47-11.dist-info/top_level.txt
knn_rk47-11.dist-info/RECORD
