Metadata-Version: 2.1
Name: knn-rk47
Version: 11
Summary: UNKNOWN
Home-page: UNKNOWN
License: UNKNOWN
Platform: UNKNOWN
Requires-Dist: hnswlib
